odoo8_addon_purchase_requisition_transport_document-8.0.0.1.0.99.dev4-py2.7-nspkg.pth
odoo8_addon_purchase_requisition_transport_document-8.0.0.1.0.99.dev4.dist-info/DESCRIPTION.rst
odoo8_addon_purchase_requisition_transport_document-8.0.0.1.0.99.dev4.dist-info/METADATA
odoo8_addon_purchase_requisition_transport_document-8.0.0.1.0.99.dev4.dist-info/RECORD
odoo8_addon_purchase_requisition_transport_document-8.0.0.1.0.99.dev4.dist-info/WHEEL
odoo8_addon_purchase_requisition_transport_document-8.0.0.1.0.99.dev4.dist-info/metadata.json
odoo8_addon_purchase_requisition_transport_document-8.0.0.1.0.99.dev4.dist-info/namespace_packages.txt
odoo8_addon_purchase_requisition_transport_document-8.0.0.1.0.99.dev4.dist-info/top_level.txt
odoo_addons/purchase_requisition_transport_document/__init__.py
odoo_addons/purchase_requisition_transport_document/__openerp__.py
odoo_addons/purchase_requisition_transport_document/i18n/fr.po
odoo_addons/purchase_requisition_transport_document/i18n/purchase_requisition_transport_document.pot
odoo_addons/purchase_requisition_transport_document/i18n/sl.po
odoo_addons/purchase_requisition_transport_document/model/__init__.py
odoo_addons/purchase_requisition_transport_document/model/purchase_requisition.py
odoo_addons/purchase_requisition_transport_document/static/description/icon.png
odoo_addons/purchase_requisition_transport_document/tests/__init__.py
odoo_addons/purchase_requisition_transport_document/tests/test_generate_po.py
odoo_addons/purchase_requisition_transport_document/view/purchase_requisition.xml
